{
  "active_counts": {
    "1": 109,
    "2": 1985,
    "3": 5544,
    "4": 4379,
    "5": 862
  },
  "active_mask_counts": {
    "10000": 109,
    "10100": 1399,
    "11000": 586,
    "11010": 3677,
    "11100": 1867,
    "11110": 4379,
    "11111": 862
  },
  "active_max": 5,
  "active_min": 0,
  "automorphisms": 2,
  "coeff": "2/3",
  "fails": 0,
  "first_fail": null,
  "graph": "sib",
  "orbit_skips": 460,
  "qmax_cuts": 991,
  "rows_checked": 12879,
  "shard_count": 64,
  "shard_index": 31,
  "verdict": "PASS",
  "weights": 923,
  "worst": {
    "N": 13,
    "Q": [
      4,
      8,
      6,
      1,
      7
    ],
    "active": [
      0,
      1,
      2,
      3
    ],
    "debt": "-167/364",
    "eta": "44/25",
    "f": [
      4,
      7
    ],
    "graph": "sib",
    "inactive_deficit": "6/13",
    "m": 5,
    "margin": "44557/27300",
    "row_sum": "4397/364",
    "s": [
      "3",
      "117/56",
      "1457/728",
      "321/91",
      "19/13"
    ],
    "side": "0000111101",
    "tau": "25/13",
    "weights": [
      1,
      1,
      1,
      1,
      1,
      1,
      2,
      1,
      2,
      2
    ]
  },
  "worst_by_active_mask": {
    "10000": {
      "N": 17,
      "Q": [
        5,
        1,
        7,
        3,
        8
      ],
      "active": [
        4
      ],
      "debt": "-78/17",
      "eta": "89/25",
      "f": [
        5,
        8
      ],
      "graph": "sib",
      "inactive_deficit": "868/663",
      "m": 8,
      "margin": "8876/1275",
      "row_sum": "433/39",
      "s": [
        "2",
        "80/39",
        "80/39",
        "2",
        "3"
      ],
      "side": "0111100000",
      "tau": "40/17",
      "weights": [
        1,
        3,
        2,
        1,
        2,
        1,
        2,
        1,
        2,
        2
      ]
    },
    "10100": {
      "N": 13,
      "Q": [
        4,
        0,
        6,
        2,
        9
      ],
      "active": [
        0,
        2
      ],
      "debt": "-1623/728",
      "eta": "44/25",
      "f": [
        4,
        9
      ],
      "graph": "sib",
      "inactive_deficit": "621/364",
      "m": 5,
      "margin": "185789/54600",
      "row_sum": "6599/728",
      "s": [
        "3",
        "23/28",
        "1457/728",
        "134/91",
        "23/13"
      ],
      "side": "0000111101",
      "tau": "25/13",
      "weights": [
        1,
        1,
        1,
        1,
        1,
        1,
        2,
        1,
        2,
        2
      ]
    },
    "11000": {
      "N": 17,
      "Q": [
        1,
        6,
        0,
        4,
        7
      ],
      "active": [
        0,
        1
      ],
      "debt": "-2192/595",
      "eta": "89/25",
      "f": [
        1,
        7
      ],
      "graph": "sib",
      "inactive_deficit": "211/119",
      "m": 8,
      "margin": "54062/8925",
      "row_sum": "404/35",
      "s": [
        "111/35",
        "108/35",
        "8/7",
        "15/7",
        "2"
      ],
      "side": "0001111001",
      "tau": "40/17",
      "weights": [
        1,
        2,
        2,
        2,
        2,
        1,
        2,
        2,
        2,
        1
      ]
    },
    "11010": {
      "N": 13,
      "Q": [
        4,
        8,
        5,
        1,
        7
      ],
      "active": [
        0,
        1,
        3
      ],
      "debt": "-391/728",
      "eta": "44/25",
      "f": [
        4,
        7
      ],
      "graph": "sib",
      "inactive_deficit": "505/364",
      "m": 5,
      "margin": "93389/54600",
      "row_sum": "8063/728",
      "s": [
        "3",
        "117/56",
        "363/364",
        "321/91",
        "19/13"
      ],
      "side": "0000111101",
      "tau": "25/13",
      "weights": [
        1,
        1,
        1,
        1,
        1,
        1,
        2,
        1,
        2,
        2
      ]
    },
    "11100": {
      "N": 13,
      "Q": [
        4,
        8,
        6,
        2,
        9
      ],
      "active": [
        0,
        1,
        2
      ],
      "debt": "-751/364",
      "eta": "44/25",
      "f": [
        4,
        9
      ],
      "graph": "sib",
      "inactive_deficit": "55/91",
      "m": 5,
      "margin": "88357/27300",
      "row_sum": "3761/364",
      "s": [
        "3",
        "117/56",
        "1457/728",
        "134/91",
        "23/13"
      ],
      "side": "0000111101",
      "tau": "25/13",
      "weights": [
        1,
        1,
        1,
        1,
        1,
        1,
        2,
        1,
        2,
        2
      ]
    },
    "11110": {
      "N": 13,
      "Q": [
        4,
        8,
        6,
        1,
        7
      ],
      "active": [
        0,
        1,
        2,
        3
      ],
      "debt": "-167/364",
      "eta": "44/25",
      "f": [
        4,
        7
      ],
      "graph": "sib",
      "inactive_deficit": "6/13",
      "m": 5,
      "margin": "44557/27300",
      "row_sum": "4397/364",
      "s": [
        "3",
        "117/56",
        "1457/728",
        "321/91",
        "19/13"
      ],
      "side": "0000111101",
      "tau": "25/13",
      "weights": [
        1,
        1,
        1,
        1,
        1,
        1,
        2,
        1,
        2,
        2
      ]
    },
    "11111": {
      "N": 13,
      "Q": [
        4,
        9,
        1,
        6,
        8
      ],
      "active": [
        0,
        1,
        2,
        3,
        4
      ],
      "debt": "-17/26",
      "eta": "44/25",
      "f": [
        4,
        8
      ],
      "graph": "sib",
      "inactive_deficit": "0",
      "m": 5,
      "margin": "3563/1950",
      "row_sum": "321/26",
      "s": [
        "3",
        "126/65",
        "219/65",
        "53/26",
        "2"
      ],
      "side": "0000011101",
      "tau": "25/13",
      "weights": [
        1,
        1,
        1,
        1,
        1,
        1,
        2,
        1,
        2,
        2
      ]
    }
  }
}